vllm_mbart/__init__.py
vllm_mbart/mbart.py
vllm_mbart-0.1.dist-info/licenses/LICENSE
vllm_mbart-0.1.dist-info/METADATA
vllm_mbart-0.1.dist-info/WHEEL
vllm_mbart-0.1.dist-info/entry_points.txt
vllm_mbart-0.1.dist-info/top_level.txt
vllm_mbart-0.1.dist-info/RECORD
