Metadata-Version: 2.4
Name: vllm_mbart
Version: 0.1
License-File: LICENSE
Requires-Dist: vllm>=0.9.0
Dynamic: license-file
Dynamic: requires-dist
